search_ncbi/__init__.py
search_ncbi/cli.py
search_ncbi/config.py
search_ncbi/ncbi_processor.py
search_ncbi/ncbi_searcher.py
search_ncbi/search_ncbi.py
search_ncbi-0.1.2.dist-info/LICENSE
search_ncbi-0.1.2.dist-info/METADATA
search_ncbi-0.1.2.dist-info/WHEEL
search_ncbi-0.1.2.dist-info/entry_points.txt
search_ncbi-0.1.2.dist-info/top_level.txt
search_ncbi-0.1.2.dist-info/RECORD
