Metadata-Version: 2.2
Name: search_ncbi
Version: 0.1.2
Summary: A package for searching and processing NCBI data
Home-page: https://github.com/Bluetea577/search_ncbi
Author: Li Mingyang
Author-email: limingyang577@163.com
Classifier: Development Status :: 3 - Alpha
Classifier: Intended Audience :: Science/Research
Classifier: License :: OSI Approved :: MIT License
Classifier: Operating System :: OS Independent
Classifier: Programming Language :: Python :: 3
Classifier: Programming Language :: Python :: 3.7
Classifier: Programming Language :: Python :: 3.8
Classifier: Programming Language :: Python :: 3.9
Classifier: Programming Language :: Python :: 3.10
Classifier: Programming Language :: Python :: 3.11
Requires-Python: >=3.7
License-File: LICENSE
Requires-Dist: biopython>=1.78
Requires-Dist: pandas>=1.3.0
Requires-Dist: tqdm>=4.46.0
Requires-Dist: xmltodict
Requires-Dist: requests
Provides-Extra: dev
Requires-Dist: pytest>=6.2.5; extra == "dev"
Requires-Dist: black>=21.9b0; extra == "dev"
Requires-Dist: flake8>=3.9.2; extra == "dev"
Dynamic: author
Dynamic: author-email
Dynamic: classifier
Dynamic: description
Dynamic: description-content-type
Dynamic: home-page
Dynamic: provides-extra
Dynamic: requires-dist
Dynamic: requires-python
Dynamic: summary
